{"cameraMode":{"drawMode":0,"name":"Shaded","section":"Shading Mode"},"sceneLighting":false,"audioPlay":false,"sceneViewState":{"showFog":true,"showMaterialUpdate":false,"showSkybox":false,"showFlares":true,"showImageEffects":true,"showParticleSystems":true},"in2DMode":false,"pivot":{"x":-2.9802322387695315e-8,"y":0.8239309787750244,"z":2.9802322387695315e-8},"rotation":{"x":-0.05994383618235588,"y":0.9058491587638855,"z":-0.13533978164196015,"w":-0.3979588449001312},"size":3.1764206886291506,"orthographic":false}